{
    "basics": {
      "name": "Gordon Carter",
      "label": "Sound Designer, Creative Coder, Researcher",
      "image": "https://imgur.com/a/AvnjlqS",
      "email": "cartergordon13@gmail.com",
      "phone": "605-940-4177",
      "location": {
        "city": "Madison",
        "countryCode": "US"
      },
      "url": "hiddenwaste.github.io",
      "summary": "Undergraduate student in Digital Sound Design and Artificial Intelligence.",
      "profiles": [
        {
          "network": "LinkedIn",
          "username": "Carter Gordon",
          "url": "https://www.linkedin.com/in/carter-gordon/"
        },
        {
          "network": "GitHub",
          "username": "HiddenWaste",
          "url": "https://github.com/HiddenWaste"
        },
        {
          "network": "Spotify",
          "username": "cartergordon13",
          "url": "https://open.spotify.com/user/cartergordon13"
        }
      ]
    },
    "work": [
      {
        "position": "Bartender",
        "company": "The Office Bar and Grill",
        "startDate": "August 2022",
        "summary": "Tasked with either opening, closing, or sometimes both. Ensure smooth operations of multiple facets of the resturaunt, train and manage new front of house staff, and general bartending tasks were some of my most prominent roles here.",
        "location": "Madison, SD",
        "highlights": []
      },
      {
        "position": "Sound Engineer",
        "company": "Madison High-School",
        "startDate": "September 2024",
        "endDate": "TBD",
        "summary": "My job was to help both map out the first setup for this high school, as well as inform the band director on what equipment was needed and why. With this setup I then ran sound for their marching band show for the school year",
        "location": "Madison, SD",
        "highlights": []
      },

      {
        "position": "Closing Expert",
        "company": "Target",
        "startDate": "May 2021",
        "endDate": "September 2023",
        "summary": "Started off hired as Closing Expert, I have since been trained in multiple other departments of our store, and am one of the few employees to do so. I have been tasked with stocking Product, assisting customers, organizing shelves, fullfillment, guest services, online orders, and many, many other facets of the store.",
        "location": "Sioux Falls, SD",
        "highlights": []
      },
      {
        "position": "Bookseller",
        "company": "Barnes & Noble",
        "startDate": "April 2019",
        "endDate": "March 2020",
        "summary": "My main priorities were throughout the store. Make sure product is in presentable condition and not in dissaray, assisting customers in finding what they need or placing orders for them, and cashiering were where I spent most of my work here",
        "location": "Sioux Falls, SD",
        "highlights": []
      }
        
    ],
    "projects": [
      {
        "name": "Resonant Soundscapes",
        "description": "Dr. Tate Carson and I traveled to all 13 state parks in South Dakota and took ambisonics recordings at each park. We then created a web app that placed them geospatially, almost like pokemon go, across DSU campus as they are laid out in South Dakota. We also made compositions from the recordings.",
         "url": "https://example.com"
      }
    ],
    "education": [
      {
        "institution": "Dakota State University",
        "area": "Digital Sound Design",
        "studyType": "Undergraduate",
        "location": "Madison, SD",
        "startDate": "2021",
        "endDate": "2025",
        "score": "In-Progress",
        "courses": ["Audio Production I - III", "Recording Sessions", "Audio Forensics"]
      },
      {
        "institution": "Dakota State University",
        "area": "Artificial Intelligence",
        "studyType": "Undergraduate",
        "location": "Madison, SD",
        "startDate": "2022",
        "endDate": "2025",
        "score": "In-Progress",
        "courses": ["Predictive Analytics", "Applications of Deep Learning", "Algorithms"]
      },
      {
        "institution": "Dakota State University",
        "area": "Creative Coding",
        "studyType": "Certificate",
        "location": "Madison, SD",
        "endDate": "2025",
        "score": "In-Progress",
        "courses": ["Creative Coding", "Interdisciplinary Coding"]
      }
    ],
    "awards": [
      {
        "title": "Research Symposium: 1st Place Research Poster",
        "date": "4-18-24",
        "issued-by": "Dakota State University",
        "summary": "1st place for the poster design for Resonant Landscapes, my SRI research project with Dr. Tate Carson. Further explained in Projects, and relative website."
      },
      {
        "title": "MUDAC 2024",
        "date": "4-06-24",
        "issued-by": "Minnesota State, Mankato"
      },
      {
        "title": "DSU Data Analytics Competition 4th Place",
        "date": "3-18-24",
        "issued-by": "Dakota State University"
      }
    ],
    "skills": [
      {
        "name": "Python",
        "level": "Advanced",
        "keywords": ["AI, ML, Data Analysis"]
      },
      {
        "name": "C, C#, C++",
        "level": "Intermediate",
        "keywords": ["coding"]
      },
      {
        "name": "Supercollider",
        "level": "Intermediate",
        "keywords": ["audio, coding"]
      },
      {
        "name": "Reaper",
        "level": "Advanced",
        "keywords": ["audio, DAW, production, recording, mixing"]
      },
      {
        "name": "Javascript",
        "level": "Intermediate",
        "keywords": ["coding, projects"]
      },
      {"name": "Ableton"},
      {"name": "Linux, Windows, Mac"},
      {"name": "Git"},
      {"name": "Raspberry Pi"},
      {"name": "Arduino / Simple Robotics"},
      {"name": "Documentation"},
      {"name": "Live Sound Mixing"},
      {"name": "Data Analysis"}
    ],
    "softSkills": [
      {
        "name": "Creative"
      },
      {
        "name": "Adaptable"
      },
      {
        "name": "Quick-Learner"
      },
      {
        "name": "Highly Sociable"
      }
    ],
    "languages": [
      {
        "language": "English",
        "fluency": "Fluent"
      },
      {
        "language": "Spanish",
        "fluency": "Intermediate"
      }
    ],
    "interests": [
      {
        "name": "Music",
        "keywords": ["audio, DAW, production, recording, mixing"]
      },
      {
        "name": "Coding",
        "keywords": ["Projects, Software, AI, ML, Data Analysis"]
      },
      {
        "name": "Reading",
        "keywords": ["Philosophy, Psychology, Poltiical Science, Sociology, History"]
      }
    ],
    "meta": {
      "template": "classic",
      "lang": "en"
    }
  }
